turkishsuffix/__init__.py
turkishsuffix/config_loader.py
turkishsuffix/suffix.py
turkishsuffix/config/exceptions.py
turkishsuffix/config/settings.py
turkishsuffix-0.3.3.dist-info/LICENSE
turkishsuffix-0.3.3.dist-info/METADATA
turkishsuffix-0.3.3.dist-info/WHEEL
turkishsuffix-0.3.3.dist-info/top_level.txt
turkishsuffix-0.3.3.dist-info/RECORD
