Metadata-Version: 2.1
Name: turkishsuffix
Version: 0.3.3
Summary: Package for managing turkish suffixes. You can find examples on GitHub page.
Home-page: http://github.com/yokunjon/turkishsuffix
Author: yokunjon
Author-email: yokunjon@gmail.com
License: MIT
Keywords: turkish suffix türkçe ek
Platform: UNKNOWN
